{
    "auth": {
        "authoritativeSet": false,
        "autoAuthMechanism": "MONGODB-CR",
        "autoAuthMechanisms": [],
        "autoAuthRestrictions": [],
        "disabled": true,
        "usersDeleted": [],
        "usersWanted": []
    },
    "backupVersions": [],
    "monitoringVersions": [],
    "mongoDbVersions": [
        {
            "name": "4.2.5-ent",
            "builds": [
                {
                    "platform": "linux",
                    "url": "https://downloads.mongodb.com/linux/mongodb-linux-x86_64-enterprise-ubuntu1604-4.2.5.tgz",
                    "gitVersion": "2261279b51ea13df08ae708ff278f0679c59dc32",
                    "architecture": "amd64",
                    "flavor": "ubuntu",
                    "minOsVersion": "16.04",
                    "maxOsVersion": "17.04",
                    "modules": [
                        "enterprise"
                    ]
                }
            ]
        }
    ],
    "mongosqlds": [],
    "mongots": [],
    "options": {
        "downloadBase": "/var/lib/mongodb-mms-automation"
    },
    "processes": [
        {
            "args2_6": {
                "net": {
                    "port": 27017,
                    "ssl": {
                        "mode": "disabled"
                    }
                },
                "systemLog": {
                    "destination": "file",
                    "path": "/var/log/mongodb-mms-automation/mongodb.log"
                }
            },
            "authSchemaVersion": 5,
            "cluster": "sample-cluster",
            "featureCompatibilityVersion": "4.2",
            "hostname": "sample-cluster-mongos-0.sample-cluster-svc.mongodb.svc.cluster.local",
            "logRotate": {
                "sizeThresholdMB": 1000.0,
                "timeThresholdHrs": 24
            },
            "name": "sample-cluster-mongos-0",
            "processType": "mongos",
            "version": "4.2.5-ent"
        },
        {
            "args2_6": {
                "net": {
                    "port": 27017,
                    "ssl": {
                        "mode": "disabled"
                    }
                },
                "systemLog": {
                    "destination": "file",
                    "path": "/var/log/mongodb-mms-automation/mongodb.log"
                }
            },
            "authSchemaVersion": 5,
            "cluster": "sample-cluster",
            "featureCompatibilityVersion": "4.2",
            "hostname": "sample-cluster-mongos-1.sample-cluster-svc.mongodb.svc.cluster.local",
            "logRotate": {
                "sizeThresholdMB": 1000.0,
                "timeThresholdHrs": 24
            },
            "name": "sample-cluster-mongos-1",
            "processType": "mongos",
            "version": "4.2.5-ent"
        },
        {
            "args2_6": {
                "net": {
                    "port": 27017,
                    "ssl": {
                        "mode": "disabled"
                    }
                },
                "replication": {
                    "replSetName": "sample-cluster-config"
                },
                "sharding": {
                    "clusterRole": "configsvr"
                },
                "storage": {
                    "dbPath": "/data"
                },
                "systemLog": {
                    "destination": "file",
                    "path": "/var/log/mongodb-mms-automation/mongodb.log"
                }
            },
            "authSchemaVersion": 5,
            "featureCompatibilityVersion": "4.2",
            "hostname": "sample-cluster-config-0.sample-cluster-cs.mongodb.svc.cluster.local",
            "logRotate": {
                "sizeThresholdMB": 1000.0,
                "timeThresholdHrs": 24
            },
            "name": "sample-cluster-config-0",
            "processType": "mongod",
            "version": "4.2.5-ent"
        },
        {
            "args2_6": {
                "net": {
                    "port": 27017,
                    "ssl": {
                        "mode": "disabled"
                    }
                },
                "replication": {
                    "replSetName": "sample-cluster-config"
                },
                "sharding": {
                    "clusterRole": "configsvr"
                },
                "storage": {
                    "dbPath": "/data"
                },
                "systemLog": {
                    "destination": "file",
                    "path": "/var/log/mongodb-mms-automation/mongodb.log"
                }
            },
            "authSchemaVersion": 5,
            "featureCompatibilityVersion": "4.2",
            "hostname": "sample-cluster-config-1.sample-cluster-cs.mongodb.svc.cluster.local",
            "logRotate": {
                "sizeThresholdMB": 1000.0,
                "timeThresholdHrs": 24
            },
            "name": "sample-cluster-config-1",
            "processType": "mongod",
            "version": "4.2.5-ent"
        },
        {
            "args2_6": {
                "net": {
                    "port": 27017,
                    "ssl": {
                        "mode": "disabled"
                    }
                },
                "replication": {
                    "replSetName": "sample-cluster-config"
                },
                "sharding": {
                    "clusterRole": "configsvr"
                },
                "storage": {
                    "dbPath": "/data"
                },
                "systemLog": {
                    "destination": "file",
                    "path": "/var/log/mongodb-mms-automation/mongodb.log"
                }
            },
            "authSchemaVersion": 5,
            "featureCompatibilityVersion": "4.2",
            "hostname": "sample-cluster-config-2.sample-cluster-cs.mongodb.svc.cluster.local",
            "logRotate": {
                "sizeThresholdMB": 1000.0,
                "timeThresholdHrs": 24
            },
            "name": "sample-cluster-config-2",
            "processType": "mongod",
            "version": "4.2.5-ent"
        },
        {
            "args2_6": {
                "net": {
                    "port": 27017,
                    "ssl": {
                        "mode": "disabled"
                    }
                },
                "replication": {
                    "replSetName": "sample-cluster-0"
                },
                "storage": {
                    "dbPath": "/data"
                },
                "systemLog": {
                    "destination": "file",
                    "path": "/var/log/mongodb-mms-automation/mongodb.log"
                }
            },
            "authSchemaVersion": 5,
            "featureCompatibilityVersion": "4.2",
            "hostname": "sample-cluster-0-0.sample-cluster-sh.mongodb.svc.cluster.local",
            "logRotate": {
                "sizeThresholdMB": 1000.0,
                "timeThresholdHrs": 24
            },
            "name": "sample-cluster-0-0",
            "processType": "mongod",
            "version": "4.2.5-ent"
        },
        {
            "args2_6": {
                "net": {
                    "port": 27017,
                    "ssl": {
                        "mode": "disabled"
                    }
                },
                "replication": {
                    "replSetName": "sample-cluster-0"
                },
                "storage": {
                    "dbPath": "/data"
                },
                "systemLog": {
                    "destination": "file",
                    "path": "/var/log/mongodb-mms-automation/mongodb.log"
                }
            },
            "authSchemaVersion": 5,
            "featureCompatibilityVersion": "4.2",
            "hostname": "sample-cluster-0-1.sample-cluster-sh.mongodb.svc.cluster.local",
            "logRotate": {
                "sizeThresholdMB": 1000.0,
                "timeThresholdHrs": 24
            },
            "name": "sample-cluster-0-1",
            "processType": "mongod",
            "version": "4.2.5-ent"
        },
        {
            "args2_6": {
                "net": {
                    "port": 27017,
                    "ssl": {
                        "mode": "disabled"
                    }
                },
                "replication": {
                    "replSetName": "sample-cluster-0"
                },
                "storage": {
                    "dbPath": "/data"
                },
                "systemLog": {
                    "destination": "file",
                    "path": "/var/log/mongodb-mms-automation/mongodb.log"
                }
            },
            "authSchemaVersion": 5,
            "featureCompatibilityVersion": "4.2",
            "hostname": "sample-cluster-0-2.sample-cluster-sh.mongodb.svc.cluster.local",
            "logRotate": {
                "sizeThresholdMB": 1000.0,
                "timeThresholdHrs": 24
            },
            "name": "sample-cluster-0-2",
            "processType": "mongod",
            "version": "4.2.5-ent"
        },
        {
            "args2_6": {
                "net": {
                    "port": 27017,
                    "ssl": {
                        "mode": "disabled"
                    }
                },
                "replication": {
                    "replSetName": "sample-cluster-1"
                },
                "storage": {
                    "dbPath": "/data"
                },
                "systemLog": {
                    "destination": "file",
                    "path": "/var/log/mongodb-mms-automation/mongodb.log"
                }
            },
            "authSchemaVersion": 5,
            "featureCompatibilityVersion": "4.2",
            "hostname": "sample-cluster-1-0.sample-cluster-sh.mongodb.svc.cluster.local",
            "logRotate": {
                "sizeThresholdMB": 1000.0,
                "timeThresholdHrs": 24
            },
            "name": "sample-cluster-1-0",
            "processType": "mongod",
            "version": "4.2.5-ent"
        },
        {
            "args2_6": {
                "net": {
                    "port": 27017,
                    "ssl": {
                        "mode": "disabled"
                    }
                },
                "replication": {
                    "replSetName": "sample-cluster-1"
                },
                "storage": {
                    "dbPath": "/data"
                },
                "systemLog": {
                    "destination": "file",
                    "path": "/var/log/mongodb-mms-automation/mongodb.log"
                }
            },
            "authSchemaVersion": 5,
            "featureCompatibilityVersion": "4.2",
            "hostname": "sample-cluster-1-1.sample-cluster-sh.mongodb.svc.cluster.local",
            "logRotate": {
                "sizeThresholdMB": 1000.0,
                "timeThresholdHrs": 24
            },
            "name": "sample-cluster-1-1",
            "processType": "mongod",
            "version": "4.2.5-ent"
        },
        {
            "args2_6": {
                "net": {
                    "port": 27017,
                    "ssl": {
                        "mode": "disabled"
                    }
                },
                "replication": {
                    "replSetName": "sample-cluster-1"
                },
                "storage": {
                    "dbPath": "/data"
                },
                "systemLog": {
                    "destination": "file",
                    "path": "/var/log/mongodb-mms-automation/mongodb.log"
                }
            },
            "authSchemaVersion": 5,
            "featureCompatibilityVersion": "4.2",
            "hostname": "sample-cluster-1-2.sample-cluster-sh.mongodb.svc.cluster.local",
            "logRotate": {
                "sizeThresholdMB": 1000.0,
                "timeThresholdHrs": 24
            },
            "name": "sample-cluster-1-2",
            "processType": "mongod",
            "version": "4.2.5-ent"
        }
    ],
    "replicaSets": [
        {
            "_id": "sample-cluster-config",
            "members": [
                {
                    "_id": 0,
                    "arbiterOnly": false,
                    "buildIndexes": true,
                    "hidden": false,
                    "host": "sample-cluster-config-0",
                    "priority": 1.0,
                    "slaveDelay": 0,
                    "votes": 1
                },
                {
                    "_id": 1,
                    "arbiterOnly": false,
                    "buildIndexes": true,
                    "hidden": false,
                    "host": "sample-cluster-config-1",
                    "priority": 1.0,
                    "slaveDelay": 0,
                    "votes": 1
                },
                {
                    "_id": 2,
                    "arbiterOnly": false,
                    "buildIndexes": true,
                    "hidden": false,
                    "host": "sample-cluster-config-2",
                    "priority": 1.0,
                    "slaveDelay": 0,
                    "votes": 1
                }
            ],
            "protocolVersion": "1"
        },
        {
            "_id": "sample-cluster-0",
            "members": [
                {
                    "_id": 0,
                    "arbiterOnly": false,
                    "buildIndexes": true,
                    "hidden": false,
                    "host": "sample-cluster-0-0",
                    "priority": 1.0,
                    "slaveDelay": 0,
                    "votes": 1
                },
                {
                    "_id": 1,
                    "arbiterOnly": false,
                    "buildIndexes": true,
                    "hidden": false,
                    "host": "sample-cluster-0-1",
                    "priority": 1.0,
                    "slaveDelay": 0,
                    "votes": 1
                },
                {
                    "_id": 2,
                    "arbiterOnly": false,
                    "buildIndexes": true,
                    "hidden": false,
                    "host": "sample-cluster-0-2",
                    "priority": 1.0,
                    "slaveDelay": 0,
                    "votes": 1
                }
            ],
            "protocolVersion": "1"
        },
        {
            "_id": "sample-cluster-1",
            "members": [
                {
                    "_id": 0,
                    "arbiterOnly": false,
                    "buildIndexes": true,
                    "hidden": false,
                    "host": "sample-cluster-1-0",
                    "priority": 1.0,
                    "slaveDelay": 0,
                    "votes": 1
                },
                {
                    "_id": 1,
                    "arbiterOnly": false,
                    "buildIndexes": true,
                    "hidden": false,
                    "host": "sample-cluster-1-1",
                    "priority": 1.0,
                    "slaveDelay": 0,
                    "votes": 1
                },
                {
                    "_id": 2,
                    "arbiterOnly": false,
                    "buildIndexes": true,
                    "hidden": false,
                    "host": "sample-cluster-1-2",
                    "priority": 1.0,
                    "slaveDelay": 0,
                    "votes": 1
                }
            ],
            "protocolVersion": "1"
        }
    ],
    "sharding": [
        {
            "collections": [],
            "configServerReplica": "sample-cluster-config",
            "draining": [],
            "managedSharding": false,
            "name": "sample-cluster",
            "shards": [
                {
                    "_id": "sample-cluster-0",
                    "rs": "sample-cluster-0",
                    "tags": []
                },
                {
                    "_id": "sample-cluster-1",
                    "rs": "sample-cluster-1",
                    "tags": []
                }
            ],
            "tags": []
        }
    ],
    "ssl": {
        "CAFilePath": "/mongodb-automation/ca.pem",
        "clientCertificateMode": "OPTIONAL"
    },
    "version": 1
}